artnex/__init__.py
artnex/audio.py
artnex/core.py
artnex/dataloader.py
artnex/dataset.py
artnex/image.py
artnex/nn.py
artnex/optim.py
artnex/utils.py
artnex/version.py
artnex-1.0.5.dist-info/LICENSE
artnex-1.0.5.dist-info/METADATA
artnex-1.0.5.dist-info/WHEEL
artnex-1.0.5.dist-info/top_level.txt
artnex-1.0.5.dist-info/RECORD
