Metadata-Version: 2.1
Name: artnex
Version: 1.0.5
Summary: ArtNex is a deep learning framework exploring the innovative fusion of art and technology.
Home-page: https://github.com/Yuan-ManX/artnex
Author: Yuan Man
Author-email: ym1076302261@gmail.com
License: MIT
Keywords: machinelearning deeplearning artificialintelligence neuralnetworks dataprocessing art-techconvergence
Platform: UNKNOWN
Classifier: Development Status :: 3 - Alpha
Classifier: Intended Audience :: Developers
Classifier: Intended Audience :: Science/Research
Classifier: License :: OSI Approved :: MIT License
Classifier: Topic :: Scientific/Engineering :: Artificial Intelligence
Classifier: Programming Language :: Python :: 3
Classifier: Programming Language :: Python :: 3.6
Classifier: Programming Language :: Python :: 3.7
Classifier: Programming Language :: Python :: 3.8
Classifier: Programming Language :: Python :: 3.9
Classifier: Programming Language :: Python :: 3.10
Classifier: Programming Language :: Python :: 3.11
License-File: LICENSE
Requires-Dist: numpy
Requires-Dist: cupy-cuda12x
Requires-Dist: cupy-cuda11x
Requires-Dist: matplotlib
Requires-Dist: requests
Requires-Dist: onnx
Requires-Dist: onnxruntime
Requires-Dist: Pillow
Requires-Dist: librosa
Requires-Dist: tqdm
